coex/__init__.py
coex/exceptions.py
coex/config/__init__.py
coex/config/settings.py
coex/core/__init__.py
coex/core/docker_manager.py
coex/core/docker_subprocess_executor.py
coex/core/executor.py
coex/core/languages.py
coex/core/lazy_installer.py
coex/core/security.py
coex/core/subprocess_executor.py
coex/utils/__init__.py
coex/utils/file_utils.py
coex/utils/validation.py
coex-0.1.19.dist-info/licenses/LICENSE
coex-0.1.19.dist-info/METADATA
coex-0.1.19.dist-info/WHEEL
coex-0.1.19.dist-info/top_level.txt
coex-0.1.19.dist-info/RECORD
