Metadata-Version: 2.4
Name: coex
Version: 0.1.19
Summary: Execute code snippets in isolated Docker environments with multi-language support and security protection
Home-page: https://github.com/torchtorchkimtorch/coex
Author: torchtorchkimtorch
Author-email: torchtorchkimtorch <mhkim092929@gmail.com>
Maintainer-email: torchtorchkimtorch <mhkim092929@gmail.com>
License: MIT License
Project-URL: Homepage, https://github.com/torchtorchkimtorch/coex
Project-URL: Documentation, https://github.com/torchtorchkimtorch/coex#readme
Project-URL: Repository, https://github.com/torchtorchkimtorch/coex
Project-URL: Bug Reports, https://github.com/torchtorchkimtorch/coex/issues
Project-URL: Changelog, https://github.com/torchtorchkimtorch/coex/blob/main/CHANGELOG.md
Keywords: docker,code-execution,sandbox,security,multi-language,testing,validation
Platform: any
Classifier: Development Status :: 4 - Beta
Classifier: Intended Audience :: Developers
Classifier: Intended Audience :: Education
Classifier: Intended Audience :: Science/Research
Classifier: License :: OSI Approved :: MIT License
Classifier: Operating System :: OS Independent
Classifier: Programming Language :: Python :: 3
Classifier: Programming Language :: Python :: 3.8
Classifier: Programming Language :: Python :: 3.9
Classifier: Programming Language :: Python :: 3.10
Classifier: Programming Language :: Python :: 3.11
Classifier: Programming Language :: Python :: 3.12
Classifier: Topic :: Software Development :: Libraries :: Python Modules
Classifier: Topic :: Software Development :: Testing
Classifier: Topic :: System :: Software Distribution
Classifier: Topic :: Education
Classifier: Topic :: Security
Requires-Python: >=3.8
License-File: LICENSE
Requires-Dist: docker>=6.0.0
Requires-Dist: requests>=2.28.0
Requires-Dist: pyyaml>=6.0
Requires-Dist: typing-extensions>=4.0.0
Provides-Extra: dev
Requires-Dist: pytest>=7.0.0; extra == "dev"
Requires-Dist: pytest-cov>=4.0.0; extra == "dev"
Requires-Dist: pytest-xdist>=3.0.0; extra == "dev"
Requires-Dist: black>=22.0.0; extra == "dev"
Requires-Dist: flake8>=5.0.0; extra == "dev"
Requires-Dist: mypy>=1.0.0; extra == "dev"
Requires-Dist: isort>=5.0.0; extra == "dev"
Provides-Extra: docs
Requires-Dist: sphinx>=5.0.0; extra == "docs"
Requires-Dist: sphinx-rtd-theme>=1.0.0; extra == "docs"
Dynamic: author
Dynamic: home-page
Dynamic: license-file
Dynamic: platform
Dynamic: requires-python
